sangfor_af_sdk/SangforAF.py
sangfor_af_sdk/__init__.py
sangfor_af_sdk/Common/BaseObject.py
sangfor_af_sdk/Common/BaseRequest.py
sangfor_af_sdk/Common/BaseResponseObject.py
sangfor_af_sdk/Common/SdkClient.py
sangfor_af_sdk/Common/__init__.py
sangfor_af_sdk/Object/Auth.py
sangfor_af_sdk/Object/CpuUsage.py
sangfor_af_sdk/Object/CpuUsages.py
sangfor_af_sdk/Object/InterfaceStatus.py
sangfor_af_sdk/Object/MemoryUsage.py
sangfor_af_sdk/Object/MemoryUsages.py
sangfor_af_sdk/Object/StatusCenterBase.py
sangfor_af_sdk/Object/SystemVersion.py
sangfor_af_sdk/Object/Uptimes.py
sangfor_af_sdk/Object/__init__.py
sangfor_af_sdk/Service/__init__.py
sangfor_af_sdk/Service/ExpandApi/__init__.py
sangfor_af_sdk/Service/Network/__init__.py
sangfor_af_sdk/Service/Object/__init__.py
sangfor_af_sdk/Service/OpsCenter/__init__.py
sangfor_af_sdk/Service/StatusCenter/CpuUsageRequest.py
sangfor_af_sdk/Service/StatusCenter/CpuUsagesRequest.py
sangfor_af_sdk/Service/StatusCenter/InterfaceStatusRequest.py
sangfor_af_sdk/Service/StatusCenter/MemoryUsageRequest.py
sangfor_af_sdk/Service/StatusCenter/MemoryUsagesRequest.py
sangfor_af_sdk/Service/StatusCenter/SystemVersionRequest.py
sangfor_af_sdk/Service/StatusCenter/UptimesRequest.py
sangfor_af_sdk/Service/StatusCenter/__init__.py
sangfor_af_sdk/Service/System/__init__.py
sangfor_af_sdk/Service/Tactics/__init__.py
sangfor_af_sdk-0.7.dist-info/METADATA
sangfor_af_sdk-0.7.dist-info/WHEEL
sangfor_af_sdk-0.7.dist-info/top_level.txt
sangfor_af_sdk-0.7.dist-info/zip-safe
sangfor_af_sdk-0.7.dist-info/RECORD
