Metadata-Version: 2.1
Name: sangfor_af_sdk
Version: 0.7
Summary: Sangfor AF SDK
Home-page: https://github.com/SpenserCai/Sangfor-AF-SDK
Author: spensercai
Author-email: spensercai@gmail.com
License: MIT
Platform: UNKNOWN
